snowcloud/__init__.py
snowcloud/delegator.py
snowcloud/flask_ext.py
snowcloud/generator.py
snowcloud/server.py
snowcloud-0.1.2.dist-info/LICENSE
snowcloud-0.1.2.dist-info/WHEEL
snowcloud-0.1.2.dist-info/METADATA
snowcloud-0.1.2.dist-info/RECORD
