Metadata-Version: 2.1
Name: snowcloud
Version: 0.1.2
Summary: Service for generating unique, time-ordered IDs across distributed worker processes.
License: MIT
Author: Brooke Chalmers
Author-email: breq@breq.dev
Requires-Python: >=3.8,<4.0
Classifier: License :: OSI Approved :: MIT License
Classifier: Programming Language :: Python :: 3
Classifier: Programming Language :: Python :: 3.8
Classifier: Programming Language :: Python :: 3.9
Requires-Dist: Flask (>=2.0.1,<3.0.0)
Requires-Dist: gunicorn (>=20.1.0,<21.0.0)
Requires-Dist: redis (>=3.5.3,<4.0.0)
Requires-Dist: requests (>=2.25.1,<3.0.0)
